setup.py
nat/__init__.py
nat/cmd.py
nat/cmdOpt.py
nat/coding.py
nat/datetime.py
nat/file.py
nat/git.py
nat/global_.py
nat/image.py
nat/json.py
nat/log.py
nat/net.py
nat/path.py
nat/phone.py
nat/plist.py
nat/string.py
nat/version.py
py_nat.egg-info/PKG-INFO
py_nat.egg-info/SOURCES.txt
py_nat.egg-info/dependency_links.txt
py_nat.egg-info/top_level.txt
test/__init__.py
test/test.py
test/archive/__init__.py
test/archive/archive.py
test/archive/archiveBxIos.py
test/archive/archiveFqAndroid.py
test/archive/archiveFqH5.py
test/archive/archiveFqIos.py
test/archive/utils.py
test/notice/__init__.py
test/notice/notice_meican.py
test/notice/notice_whats_new.py
thd/__init__.py
thd/calendar/__init__.py
thd/calendar/ics.py
thd/ios/__init__.py
thd/ios/ipa.py
thd/qrcode/__init__.py
thd/qrcode/nat_qrcode.py
thd/wechat/__init__.py
thd/wechat/group_robot.py