Metadata-Version: 1.0
Name: py-nat
Version: 1.0.23
Summary: Basic Library
Home-page: https://github.com/natloc-developer/py-nat.git
Author: natloc_developer
Author-email: natloc_developer@foxmail.com
License: UNKNOWN
Platform: any
